Data_mem/Data_Memory.v

module DataMem #(
    parameter N=64
) (
    output reg [N-1:0]outData,
    input dmem_err,
    // input  reg [7:0]memory[65535:0],
    input [N-1:0] inData,
    input [N-1:0] inAdd,
    input rEn,wEn,clk,reset
);
    
    reg [7:0]memory[65535:0];

    // integer i,j;
    always @(posedge clk)
    begin
        // for( i=inAdd;i<inAdd+8 && dmem_err;i=i+1)
        // begin
            if(~dmem_err)
            begin
                if(rEn&~wEn&~reset)
                begin
                    // outData[i-inAdd:i-inAdd+7]<=memory[i];
                    // outData[j:j+7]<=memory[i];
                    outData[7:0]<=memory[inAdd+0];
                    outData[15:8]<=memory[inAdd+1];
                    outData[23:16]<=memory[inAdd+2];
                    outData[31:24]<=memory[inAdd+3];
                    outData[39:32]<=memory[inAdd+4];
                    outData[47:40]<=memory[inAdd+5];
                    outData[55:48]<=memory[inAdd+6];
                    outData[63:56]<=memory[inAdd+7];

                end
                if(~rEn&wEn&~reset)
                begin
                    // memory[i]<=inData[i-inAdd:i-inAdd+7];
                    // memory[i]<=inData[j:j+7];
                    memory[inAdd+0]<=inData[7:0];
                    memory[inAdd+1]<=inData[15:8];
                    memory[inAdd+2]<=inData[23:16];
                    memory[inAdd+3]<=inData[31:24];
                    memory[inAdd+4]<=inData[39:32];
                    memory[inAdd+5]<=inData[47:40];
                    memory[inAdd+6]<=inData[55:48];
                    memory[inAdd+7]<=inData[63:56];
                end
                if(reset)
                begin
                    outData[7:0]<=8'b0;
                    outData[15:8]<=8'b0;
                    outData[23:16]<=8'b0;
                    outData[31:24]<=8'b0;
                    outData[39:32]<=8'b0;
                    outData[47:40]<=8'b0;
                    outData[55:48]<=8'b0;
                    outData[63:56]<=8'b0;
                    memory[inAdd+0]<=8'b0;
                    memory[inAdd+1]<=8'b0;
                    memory[inAdd+2]<=8'b0;
                    memory[inAdd+3]<=8'b0;
                    memory[inAdd+4]<=8'b0;
                    memory[inAdd+5]<=8'b0;
                    memory[inAdd+6]<=8'b0;
                    memory[inAdd+7]<=8'b0;
                end
            end
            else
            begin
                    outData[7:0]<=8'b0;
                    outData[15:8]<=8'b0;
                    outData[23:16]<=8'b0;
                    outData[31:24]<=8'b0;
                    outData[39:32]<=8'b0;
                    outData[47:40]<=8'b0;
                    outData[55:48]<=8'b0;
                    outData[63:56]<=8'b0;
            end
        // end
    end

endmodule

Data_mem/Data_memWrap.v
`include "Data_Memory.v"

module DataWrap (
    output [63:0]valM,
    output reg[1:0]stat,
    // input [7:0]memory[65535:0],
    // output reg dmem_err,
    // output reg [63:0]inData,inAdd,
    // output reg rEn,wEn,

    input [63:0]valE,
    input [63:0]valA,
    input [63:0]valP,
    input [3:0]icode,
    input instr_valid,imem_error,clk,rst
);
    reg dmem_err;
    reg rEn,wEn;
    reg [63:0]inData,inAdd;
    // This is inpendent of clock, combinational logic part of data memory
    always @ (*)
    begin
        case(icode)
            4:begin     //rmmovq
                 rEn<=0;
                wEn<=1;
                inData<=valA;
                inAdd<=valE;
            end

            5:begin     //mrmovq
                rEn<=1;
                wEn<=0;
                inData<=64'd0;
                inAdd<=valE;
            end
            10: begin   //pushq
                rEn<=0; wEn<=1;
                inData<=valA;
                inAdd<=valE;
            end

            11: begin   //popq
                rEn<=1; wEn<=0;
                inData<=0;
                inAdd<=valA;
            end
            8: begin    //call
                rEn<=0;
                wEn<=1;
                inData<=valP;
                inAdd<=valE;
            end
            9: begin    //ret
                rEn<=1; wEn<=0;
                inData<=0;
                inAdd<=valA;
            end
            default: begin
                     rEn<=0;
                     wEn<=0;
            end
        endcase
        dmem_err<=(inAdd+7>=65536)||(rEn&wEn);
        if(icode==0)
            stat<=2'd1;
        else if(dmem_err==1||imem_error==1)
            stat<=2'd2;
        else if(!instr_valid)
            stat<=2'd3;
        else
            stat<=2'd0;
    end
    // DataMem #(.N(64)) A(.outData(valM),.dmem_err(dmem_err),.memory(memory),.inData(inData),.inAdd(inAdd),.rEn(rEn),.wEn(wEn),.clk(clk),.reset(1'b0));

    // This module only updates at positive edge
    DataMem #(.N(64)) A(.outData(valM),.dmem_err(dmem_err),.inData(inData),.inAdd(inAdd),.rEn(rEn),.wEn(wEn),.clk(clk),.reset(rst));
    

endmodule

Data_mem/test.v
`include "Data_memWrap.v"
`default_nettype none

module tb_Data_memWrap;
wire [63:0]valM,inData,inAdd;
wire [1:0]stat;
wire dmem_err;

reg clk;
reg rst;
reg [63:0]valE;
reg [63:0]valA;
reg [63:0]valP;
reg [3:0]icode;
reg instr_valid,imem_error;
reg [7:0]memory[65535:0];

reg cond;

DataWrap uut
(
    .valM(valM),
    .stat(stat),
    // .dmem_err(dmem_err),
    // .inAdd(inAdd),
    // .inData(inData),
    .valE(valE),
    .valA(valA),
    .valP(valP),
    .icode(icode),
    .instr_valid(instr_valid),
    .imem_error(imem_error),
    .clk(clk),.rst(rst)
);

localparam CLK_PERIOD = 30;
always #(CLK_PERIOD/2) clk=~clk;

// always #(CLK_PERIOD/2) $display($time," clk=%b, icode=%d, valM=%d , stat=%b, valE=%d, dmem=%b, inADD=%d , inData=%d",clk,icode,valM,stat,valE,dmem_err,cond,inData);

initial begin
    $dumpfile("tb_Data_memWrap.vcd");
    $dumpvars(0, tb_Data_memWrap);
    $monitor($time," clk=%b, icode=%d, valM=%d , stat=%b, valE=%d",clk,icode,valM,stat,valE);//,dmem_err,cond,inData);
end

initial begin
    clk<=0;
    #1 rst<=0;
    icode<=4;
    valE<=65536;
    valA<=64'd12;
    valP<=64'd10;
    imem_error<=0;instr_valid<=1;

    cond<=(inAdd+7>=65536);
    #20;
    icode<=5;
    valE<=64'd58;
    valP<=64'd11;
    imem_error<=0;instr_valid<=1;
    #40;
    icode<=4;
    valE<=64'd58;
    valP<=64'd11;
    imem_error<=0;instr_valid<=1;

    #40;
    icode<=9;
    valE<=64'd58;
    valA<=64'd58;
    valP<=64'd11;
    imem_error<=0;instr_valid<=1;

    #40;

    $finish(2);
end

endmodule

`default_nettype wire

Data_mem/tb_Data_memWrap.vcd
$date
	Thu Feb 10 19:18:09 2022
$end
$version
	Icarus Verilog
$end
$timescale
	1s
$end
$scope module tb_Data_memWrap $end
$var wire 64 ! inAdd [63:0] $end
$var wire 64 " valM [63:0] $end
$var wire 2 # stat [1:0] $end
$var reg 1 $ clk $end
$var reg 1 % cond $end
$var reg 4 & icode [3:0] $end
$var reg 1 ' imem_error $end
$var reg 1 ( instr_valid $end
$var reg 1 ) rst $end
$var reg 64 * valA [63:0] $end
$var reg 64 + valE [63:0] $end
$var reg 64 , valP [63:0] $end
$scope module uut $end
$var wire 1 $ clk $end
$var wire 4 - icode [3:0] $end
$var wire 1 ' imem_error $end
$var wire 1 ( instr_valid $end
$var wire 1 ) rst $end
$var wire 64 . valA [63:0] $end
$var wire 64 / valE [63:0] $end
$var wire 64 0 valP [63:0] $end
$var wire 64 1 valM [63:0] $end
$var reg 1 2 dmem_err $end
$var reg 64 3 inAdd [63:0] $end
$var reg 64 4 inData [63:0] $end
$var reg 1 5 rEn $end
$var reg 2 6 stat [1:0] $end
$var reg 1 7 wEn $end
$scope module A $end
$var wire 1 $ clk $end
$var wire 1 2 dmem_err $end
$var wire 64 8 inAdd [63:0] $end
$var wire 64 9 inData [63:0] $end
$var wire 1 5 rEn $end
$var wire 1 ) reset $end
$var wire 1 7 wEn $end
$var reg 64 : outData [63:0] $end
$upscope $end
$upscope $end
$upscope $end
$enddefinitions $end
#0
$dumpvars
bx :
bx 9
bx 8
x7
bx 6
x5
bx 4
bx 3
x2
bx 1
bx 0
bx /
bx .
bx -
bx ,
bx +
bx *
x)
x(
x'
bx &
x%
0$
bx #
bx "
bz !
$end
#1
12
b10 #
b10 6
b10000000000000000 3
b10000000000000000 8
b1100 4
b1100 9
17
05
1(
0'
b1010 ,
b1010 0
b1100 *
b1100 .
b10000000000000000 +
b10000000000000000 /
b100 &
b100 -
0)
#15
b0 "
b0 1
b0 :
1$
#21
b0 #
b0 6
02
b111010 3
b111010 8
b0 4
b0 9
07
15
b1011 ,
b1011 0
b111010 +
b111010 /
b101 &
b101 -
#30
0$
#45
bx "
bx 1
bx :
1$
#60
0$
#61
b1100 4
b1100 9
17
05
b100 &
b100 -
#75
1$
#90
0$
#101
b0 4
b0 9
07
15
b111010 *
b111010 .
b1001 &
b1001 -
#105
b1100 "
b1100 1
b1100 :
1$
